systemd_py/__init__.py
systemd_py/builders/__init__.py
systemd_py/builders/_builder.py
systemd_py/builders/install.py
systemd_py/builders/service.py
systemd_py/builders/socket.py
systemd_py/builders/unit.py
systemd_py/commands/__init__.py
systemd_py/commands/cli/__init__.py
systemd_py/commands/cli/main.py
systemd_py/commands/interactive/__init__.py
systemd_py/commands/interactive/main.py
systemd_py/commands/main.py
systemd_py/core/__init__.py
systemd_py/core/enums/__init__.py
systemd_py/core/enums/_enums.py
systemd_py/core/enums/restart.py
systemd_py/core/enums/type.py
systemd_py/core/models/__init__.py
systemd_py/core/models/_models.py
systemd_py/core/models/install.py
systemd_py/core/models/service.py
systemd_py/core/models/socket.py
systemd_py/core/models/unit.py
systemd_py/core/types/__init__.py
systemd_py/core/types/_types.py
systemd_py/exceptions.py
systemd_py/interactive/__init__.py
systemd_py/interactive/_interactive.py
systemd_py/interactive/simple_builder.py
systemd_py/main.py
systemd_py/utils/__init__.py
systemd_py/utils/daemon.py
systemd_py/utils/files.py
systemd_py/utils/terminal/__init__.py
systemd_py/utils/terminal/clear.py
systemd_py/utils/terminal/inputer.py
systemd_py-0.3.3.dist-info/entry_points.txt
systemd_py-0.3.3.dist-info/METADATA
systemd_py-0.3.3.dist-info/WHEEL
systemd_py-0.3.3.dist-info/RECORD
